[
  "snapshot",
  {
    "mapName": "",
    "speed": 1,
    "innerWidth": 2080,
    "innerHeight": 1518,
    "sharedKeys": [
      1,
      "snapshot",
      2,
      "PlayerPrivateData",
      3,
      "Game",
      4,
      "battle_royale",
      5,
      "fun",
      6,
      "arena1",
      7,
      "coins",
      8,
      "mapReplaceTile",
      9,
      "Rope",
      10,
      "DebugPoint",
      11,
      "Tree",
      12,
      "Obstacle",
      13,
      "Citizen",
      14,
      "Monster",
      15,
      "Animal",
      16,
      "Sandworm",
      17,
      "Pedestal",
      18,
      "Campfire",
      19,
      "FlagBase",
      20,
      "ClaimableFlag",
      21,
      "Gate",
      22,
      "FortFlag",
      23,
      "Flag",
      24,
      "Crate",
      25,
      "Guillotine",
      26,
      "Spikes",
      27,
      "Quicksand",
      28,
      "ThrowingKnife",
      29,
      "Projectile",
      30,
      "Wave",
      31,
      "Pickup",
      32,
      "Stone",
      33,
      "Mine",
      34,
      "Ball",
      35,
      "SoccerGoalLine",
      36,
      "Beam",
      37,
      "Grenade",
      38,
      "Container",
      39,
      "Door",
      40,
      "Stove",
      41,
      "Marker",
      42,
      "hit",
      43,
      "idle",
      44,
      "orc_archer",
      45,
      "bow",
      46,
      "hood",
      47,
      "no_shield",
      48,
      "default_voice",
      49,
      "no_cape",
      50,
      "medical_cupboard1",
      51,
      "fort",
      52,
      "armory_wardrobe1",
      53,
      "randoms",
      54,
      "barbarian_miner",
      55,
      "hammer",
      56,
      "no_helmet",
      57,
      "barbarian_sentry",
      58,
      "club",
      59,
      "orc_berserker",
      60,
      "double_axe",
      61,
      "elf_ears",
      62,
      "mohawk_hair",
      63,
      "orc_tank",
      64,
      "shield_heavy",
      65,
      "orc_warrior",
      66,
      "axe",
      67,
      "viking_helmet",
      68,
      "shield_usa",
      69,
      "barbarian_saper",
      70,
      null,
      71,
      "backpack",
      72,
      "barbarian_giant",
      73,
      "house",
      74,
      "default",
      75,
      "mine",
      76,
      "knife",
      77,
      "stun",
      78,
      "hero",
      79,
      "fedora",
      80,
      "desert",
      81,
      "attack",
      82,
      "charge",
      83,
      "jump",
      84,
      "launchArrow",
      85,
      "arrow",
      86,
      "jumpAttack",
      87,
      "roll",
      88,
      "throw",
      89,
      "stone",
      90,
      "block",
      91,
      "blocked",
      92,
      "dying",
      93,
      "kick",
      94,
      "dead",
      95,
      "powerHit",
      96,
      "fallBack",
      97,
      "fallFront",
      98,
      "spin",
      99,
      "shield_wooden",
      100,
      "ice_staff",
      101,
      "noble_cape",
      102,
      "operate"
    ],
    "entities": [
      [
        1,
        39,
        false,
        -1792,
        -1067,
        false,
        0
      ],
      [
        2,
        40,
        false,
        -1760,
        -1298,
        0
      ],
      [
        3,
        13,
        false,
        -1773,
        -1194,
        44,
        false,
        0,
        [
          82
        ],
        13,
        0,
        0,
        "Orc Archer",
        false,
        40,
        4,
        0,
        0,
        "",
        "human",
        0,
        0,
        45,
        46,
        47,
        48,
        {},
        49,
        0
      ],
      [
        4,
        39,
        false,
        1408,
        1353,
        false,
        1
      ],
      [
        5,
        40,
        false,
        1440,
        1122,
        0
      ],
      [
        6,
        13,
        false,
        1417,
        1218,
        44,
        false,
        0,
        [
          82
        ],
        6,
        0,
        1,
        "Orc Archer",
        false,
        40,
        4,
        0,
        0,
        "",
        "human",
        0,
        0,
        45,
        46,
        47,
        48,
        {},
        49,
        0
      ],
      [
        7,
        20,
        false,
        31,
        29,
        -1,
        0,
        0
      ],
      [
        8,
        38,
        false,
        92,
        -287,
        [
          [
            75,
            1
          ]
        ],
        50,
        false
      ],
      [
        9,
        21,
        false,
        -64,
        308,
        255,
        0,
        40
      ],
      [
        10,
        13,
        false,
        -289,
        -127,
        44,
        false,
        0,
        [
          82
        ],
        47,
        2,
        4,
        "Orc Archer",
        false,
        40,
        4,
        0,
        0,
        "",
        "human",
        0,
        0,
        45,
        46,
        47,
        48,
        {},
        49,
        0
      ],
      [
        11,
        13,
        false,
        -285,
        219,
        44,
        false,
        0,
        [
          82
        ],
        15,
        0,
        4,
        "Orc Archer",
        false,
        40,
        4,
        0,
        0,
        "",
        "human",
        0,
        0,
        45,
        46,
        47,
        48,
        {},
        49,
        0
      ],
      [
        12,
        13,
        false,
        338,
        245,
        44,
        false,
        0,
        [
          43
        ],
        0,
        0,
        4,
        "Orc Archer",
        false,
        40,
        4,
        0,
        0,
        "",
        "human",
        0,
        0,
        45,
        46,
        47,
        48,
        {},
        49,
        0
      ],
      [
        13,
        13,
        false,
        337,
        -166,
        44,
        false,
        0,
        [
          43
        ],
        0,
        0,
        4,
        "Orc Archer",
        false,
        40,
        4,
        0,
        0,
        "",
        "human",
        0,
        0,
        45,
        46,
        47,
        48,
        {},
        49,
        0
      ],
      [
        15,
        31,
        false,
        248,
        -71,
        248,
        -71,
        "potion_stamina"
      ],
      [
        14,
        17,
        false,
        248,
        -71
      ],
      [
        16,
        22,
        false,
        -59,
        196,
        255
      ],
      [
        17,
        22,
        false,
        124,
        194,
        255
      ],
      [
        18,
        22,
        false,
        377,
        -275,
        255
      ],
      [
        19,
        22,
        false,
        -317,
        -270,
        255
      ],
      [
        20,
        41,
        false,
        52,
        18,
        51,
        true,
        "fort"
      ],
      [
        21,
        38,
        false,
        -16,
        -275,
        [
          [
            76,
            1
          ]
        ],
        52,
        false
      ],
      [
        22,
        40,
        false,
        32,
        -286,
        0
      ],
      [
        23,
        12,
        false,
        1192,
        -968,
        0,
        53
      ],
      [
        24,
        12,
        false,
        1447,
        -975,
        1,
        53
      ],
      [
        25,
        12,
        false,
        1201,
        -749,
        1,
        53
      ],
      [
        26,
        12,
        false,
        1430,
        -729,
        0,
        53
      ],
      [
        27,
        20,
        false,
        1309,
        -855,
        -1,
        0,
        0
      ],
      [
        28,
        39,
        false,
        1280,
        -1067,
        false,
        2
      ],
      [
        29,
        13,
        false,
        1099,
        -922,
        54,
        false,
        0,
        [
          43
        ],
        0,
        0,
        3,
        "Barbarian",
        false,
        60,
        6,
        0,
        0,
        "",
        "human",
        0,
        0,
        55,
        56,
        47,
        48,
        {},
        49,
        0
      ],
      [
        30,
        13,
        false,
        1509,
        -765,
        57,
        false,
        0,
        [
          43
        ],
        0,
        0,
        3,
        "Barbarian",
        false,
        60,
        6,
        0,
        0,
        "",
        "human",
        0,
        0,
        58,
        56,
        47,
        48,
        {},
        49,
        0
      ],
      [
        31,
        13,
        false,
        1085,
        -745,
        57,
        false,
        0,
        [
          43
        ],
        0,
        0,
        3,
        "Barbarian",
        false,
        60,
        6,
        0,
        0,
        "",
        "human",
        0,
        0,
        58,
        56,
        47,
        48,
        {},
        49,
        0
      ],
      [
        32,
        24,
        false,
        1315,
        -1174,
        18,
        false
      ],
      [
        33,
        24,
        false,
        1240,
        -992,
        15,
        false
      ],
      [
        34,
        24,
        false,
        1240,
        -961,
        15,
        false
      ],
      [
        35,
        24,
        false,
        1156,
        -692,
        15,
        false
      ],
      [
        36,
        24,
        false,
        1191,
        -692,
        14,
        false
      ],
      [
        37,
        24,
        false,
        1244,
        -930,
        14,
        false
      ],
      [
        38,
        24,
        false,
        1408,
        -920,
        14,
        false
      ],
      [
        39,
        24,
        false,
        1480,
        -679,
        14,
        false
      ],
      [
        40,
        24,
        false,
        1480,
        -706,
        13,
        false
      ],
      [
        41,
        24,
        false,
        1480,
        -730,
        13,
        false
      ],
      [
        42,
        24,
        false,
        1448,
        -924,
        12,
        false
      ],
      [
        43,
        24,
        false,
        1230,
        -693,
        11,
        false
      ],
      [
        44,
        24,
        false,
        1473,
        -921,
        11,
        false
      ],
      [
        45,
        24,
        false,
        1136,
        -983,
        0,
        false
      ],
      [
        46,
        24,
        false,
        1136,
        -943,
        1,
        false
      ],
      [
        47,
        24,
        false,
        1493,
        -956,
        3,
        false
      ],
      [
        48,
        24,
        false,
        1106,
        -699,
        5,
        false
      ],
      [
        50,
        31,
        false,
        1192,
        -1193,
        1192,
        -1193,
        "bomb"
      ],
      [
        49,
        17,
        false,
        1192,
        -1193
      ],
      [
        52,
        31,
        false,
        1432,
        -1193,
        1432,
        -1193,
        "mine"
      ],
      [
        51,
        17,
        false,
        1432,
        -1193
      ],
      [
        53,
        24,
        false,
        1218,
        -1127,
        1,
        false
      ],
      [
        54,
        24,
        false,
        1245,
        -1151,
        2,
        false
      ],
      [
        55,
        24,
        false,
        1217,
        -1163,
        0,
        false
      ],
      [
        56,
        24,
        false,
        1405,
        -1134,
        5,
        false
      ],
      [
        57,
        24,
        false,
        1381,
        -1165,
        6,
        false
      ],
      [
        58,
        24,
        false,
        1367,
        -1132,
        7,
        false
      ],
      [
        59,
        39,
        false,
        -1088,
        33,
        true,
        -1
      ],
      [
        60,
        13,
        false,
        -1092,
        -76,
        44,
        false,
        0,
        [
          43
        ],
        0,
        0,
        4,
        "Orc Archer",
        false,
        40,
        4,
        0,
        0,
        "",
        "human",
        0,
        0,
        45,
        46,
        47,
        48,
        {},
        49,
        0
      ],
      [
        61,
        20,
        false,
        -1050,
        -49,
        -1,
        0,
        0
      ],
      [
        62,
        11,
        false,
        59,
        -1333,
        5,
        true
      ],
      [
        63,
        11,
        false,
        261,
        -1200,
        5,
        false
      ],
      [
        64,
        11,
        false,
        343,
        -1436,
        5,
        false
      ],
      [
        65,
        13,
        false,
        209,
        -1288,
        59,
        false,
        0,
        [
          43
        ],
        0,
        0,
        4,
        "Orc Warrior",
        false,
        80,
        8,
        0,
        0,
        "",
        "human",
        0,
        0,
        60,
        61,
        47,
        48,
        {},
        62,
        0
      ],
      [
        66,
        13,
        false,
        137,
        -1459,
        63,
        false,
        0,
        [
          43
        ],
        0,
        0,
        4,
        "Orc Tank",
        false,
        60,
        6,
        6,
        0,
        "",
        "human",
        0,
        0,
        55,
        61,
        64,
        48,
        {},
        49,
        0
      ],
      [
        67,
        13,
        false,
        308,
        -1409,
        65,
        false,
        0,
        [
          43
        ],
        0,
        0,
        4,
        "Orc Warrior",
        false,
        60,
        6,
        0,
        0,
        "",
        "human",
        0,
        0,
        66,
        67,
        68,
        48,
        {},
        49,
        0
      ],
      [
        68,
        18,
        false,
        208,
        -1375,
        0
      ],
      [
        69,
        32,
        false,
        475,
        -499,
        "0",
        false
      ],
      [
        70,
        32,
        false,
        502,
        -476,
        "1",
        false
      ],
      [
        71,
        32,
        false,
        465,
        -474,
        "15",
        false
      ],
      [
        72,
        32,
        false,
        507,
        -508,
        "4",
        false
      ],
      [
        73,
        32,
        false,
        491,
        -457,
        "5",
        false
      ],
      [
        74,
        32,
        false,
        526,
        -488,
        "6",
        false
      ],
      [
        75,
        32,
        false,
        521,
        -461,
        "7",
        false
      ],
      [
        76,
        24,
        false,
        479,
        -596,
        5,
        false
      ],
      [
        77,
        13,
        false,
        403,
        -517,
        54,
        false,
        0,
        [
          43
        ],
        0,
        0,
        3,
        "Barbarian",
        false,
        60,
        6,
        0,
        0,
        "",
        "human",
        0,
        0,
        55,
        56,
        47,
        48,
        {},
        49,
        0
      ],
      [
        78,
        13,
        false,
        1294,
        982,
        69,
        false,
        0,
        [
          94
        ],
        5,
        0,
        3,
        "Barbarian",
        true,
        0,
        6,
        0,
        0,
        "",
        "human",
        0,
        0,
        70,
        56,
        47,
        48,
        {},
        71,
        0
      ],
      [
        79,
        13,
        false,
        1397,
        749,
        54,
        false,
        0,
        [
          94
        ],
        3,
        0,
        3,
        "Barbarian",
        true,
        0,
        6,
        0,
        0,
        "",
        "human",
        0,
        0,
        55,
        56,
        47,
        48,
        {},
        49,
        0
      ],
      [
        80,
        13,
        false,
        1261,
        607,
        57,
        false,
        0,
        [
          94
        ],
        60,
        0,
        3,
        "Barbarian",
        true,
        0,
        6,
        0,
        0,
        "",
        "human",
        0,
        0,
        58,
        56,
        47,
        48,
        {},
        49,
        0
      ],
      [
        81,
        24,
        false,
        1050,
        721,
        5,
        false
      ],
      [
        82,
        24,
        false,
        1010,
        733,
        7,
        false
      ],
      [
        83,
        24,
        false,
        1034,
        752,
        6,
        false
      ],
      [
        84,
        32,
        false,
        985,
        753,
        "15",
        false
      ],
      [
        85,
        32,
        false,
        985,
        724,
        "14",
        false
      ],
      [
        86,
        32,
        false,
        959,
        734,
        "13",
        false
      ],
      [
        87,
        13,
        false,
        -866,
        -972,
        72,
        false,
        0,
        [
          43
        ],
        0,
        0,
        3,
        "Barbarian",
        false,
        200,
        20,
        0,
        0,
        "",
        "human",
        0,
        0,
        58,
        56,
        47,
        48,
        {},
        49,
        0
      ],
      [
        88,
        24,
        false,
        -861,
        -1140,
        18,
        false
      ],
      [
        89,
        39,
        false,
        -896,
        -1067,
        true,
        -1
      ],
      [
        90,
        24,
        false,
        -416,
        -675,
        2,
        false
      ],
      [
        91,
        24,
        false,
        -383,
        -676,
        1,
        false
      ],
      [
        92,
        24,
        false,
        -353,
        -647,
        0,
        false
      ],
      [
        93,
        24,
        false,
        -413,
        -638,
        3,
        false
      ],
      [
        94,
        24,
        false,
        -350,
        -677,
        4,
        false
      ],
      [
        95,
        24,
        false,
        -157,
        -543,
        8,
        false
      ],
      [
        96,
        24,
        false,
        -106,
        -539,
        6,
        false
      ],
      [
        97,
        24,
        false,
        -147,
        -515,
        7,
        false
      ],
      [
        98,
        24,
        false,
        -106,
        -514,
        0,
        false
      ],
      [
        99,
        13,
        false,
        -304,
        -359,
        57,
        false,
        0,
        [
          94
        ],
        46,
        0,
        3,
        "Barbarian",
        true,
        0,
        6,
        0,
        0,
        "",
        "human",
        0,
        0,
        58,
        56,
        47,
        48,
        {},
        49,
        0
      ],
      [
        100,
        13,
        false,
        -254,
        -507,
        57,
        false,
        0,
        [
          94
        ],
        47,
        0,
        3,
        "Barbarian",
        true,
        0,
        6,
        0,
        0,
        "",
        "human",
        0,
        0,
        58,
        56,
        47,
        48,
        {},
        49,
        0
      ],
      [
        101,
        18,
        false,
        -288,
        -528,
        0
      ],
      [
        102,
        11,
        false,
        -1827,
        -790,
        5,
        false
      ],
      [
        103,
        11,
        false,
        -1638,
        -716,
        5,
        true
      ],
      [
        104,
        11,
        false,
        -1820,
        -614,
        5,
        false
      ],
      [
        105,
        13,
        false,
        -1889,
        -934,
        65,
        false,
        1,
        [
          43
        ],
        53,
        0,
        4,
        "Orc Warrior",
        false,
        60,
        6,
        0,
        0,
        "",
        "human",
        0,
        0,
        66,
        67,
        68,
        48,
        {},
        49,
        0
      ],
      [
        106,
        13,
        false,
        -1688,
        -973,
        65,
        false,
        0,
        [
          90
        ],
        42,
        0,
        4,
        "Orc Warrior",
        false,
        60,
        6,
        0,
        0,
        "",
        "human",
        0,
        0,
        66,
        67,
        68,
        48,
        {},
        49,
        0
      ],
      [
        107,
        13,
        false,
        -1714,
        -777,
        65,
        false,
        0,
        [
          90
        ],
        45,
        0,
        4,
        "Orc Warrior",
        false,
        60,
        6,
        0,
        0,
        "",
        "human",
        0,
        0,
        66,
        67,
        68,
        48,
        {},
        49,
        0
      ],
      [
        108,
        13,
        false,
        -1716,
        -959,
        63,
        false,
        1,
        [
          43
        ],
        43,
        0,
        4,
        "Orc Tank",
        false,
        60,
        6,
        6,
        0,
        "",
        "human",
        0,
        0,
        55,
        61,
        64,
        48,
        {},
        49,
        0
      ],
      [
        109,
        39,
        false,
        -768,
        1265,
        true,
        -1
      ],
      [
        110,
        13,
        false,
        -772,
        1156,
        44,
        false,
        0,
        [
          43
        ],
        0,
        0,
        4,
        "Orc Archer",
        false,
        40,
        4,
        0,
        0,
        "",
        "human",
        0,
        0,
        45,
        46,
        47,
        48,
        {},
        49,
        0
      ],
      [
        111,
        20,
        false,
        -730,
        1183,
        -1,
        0,
        0
      ],
      [
        112,
        24,
        false,
        -971,
        832,
        6,
        false
      ],
      [
        113,
        24,
        false,
        -971,
        866,
        7,
        false
      ],
      [
        114,
        24,
        false,
        -922,
        827,
        8,
        false
      ],
      [
        115,
        24,
        false,
        -879,
        830,
        6,
        false
      ],
      [
        116,
        24,
        false,
        -869,
        863,
        4,
        false
      ],
      [
        117,
        24,
        false,
        -899,
        863,
        7,
        false
      ],
      [
        118,
        24,
        false,
        -929,
        862,
        1,
        false
      ],
      [
        119,
        39,
        false,
        -960,
        913,
        false,
        -1
      ],
      [
        120,
        41,
        false,
        -928,
        840,
        73,
        false,
        null
      ],
      [
        121,
        13,
        false,
        -1132,
        1262,
        65,
        false,
        0,
        [
          43
        ],
        0,
        0,
        4,
        "Orc Warrior",
        false,
        60,
        6,
        0,
        0,
        "",
        "human",
        0,
        0,
        66,
        67,
        68,
        48,
        {},
        49,
        0
      ],
      [
        123,
        31,
        false,
        -968,
        1326,
        -968,
        1326,
        "potion_haste"
      ],
      [
        122,
        17,
        false,
        -968,
        1326
      ],
      [
        124,
        24,
        false,
        -982,
        1242,
        5,
        false
      ],
      [
        125,
        24,
        false,
        -939,
        1253,
        6,
        false
      ],
      [
        126,
        24,
        false,
        -950,
        1214,
        7,
        false
      ],
      [
        127,
        39,
        false,
        -1088,
        1397,
        false,
        -1
      ],
      [
        128,
        41,
        false,
        -1054,
        1260,
        73,
        false,
        null
      ],
      [
        129,
        39,
        false,
        -1216,
        -231,
        false,
        -1
      ],
      [
        131,
        31,
        false,
        -1288,
        -335,
        -1288,
        -335,
        "bomb"
      ],
      [
        130,
        17,
        false,
        -1288,
        -335
      ],
      [
        132,
        24,
        false,
        -1199,
        -349,
        5,
        false
      ],
      [
        133,
        24,
        false,
        -1149,
        -312,
        6,
        false
      ],
      [
        134,
        24,
        false,
        -1150,
        -354,
        7,
        false
      ],
      [
        135,
        24,
        false,
        -1123,
        -339,
        13,
        false
      ],
      [
        136,
        24,
        false,
        -1116,
        -376,
        16,
        false
      ],
      [
        137,
        41,
        false,
        -1218,
        -326,
        73,
        false,
        null
      ],
      [
        138,
        39,
        false,
        0,
        1177,
        false,
        -1
      ],
      [
        139,
        13,
        false,
        101,
        1039,
        65,
        false,
        0,
        [
          43
        ],
        0,
        0,
        4,
        "Orc Warrior",
        false,
        60,
        6,
        0,
        0,
        "",
        "human",
        0,
        0,
        66,
        67,
        68,
        48,
        {},
        49,
        0
      ],
      [
        141,
        31,
        false,
        -72,
        985,
        -72,
        985,
        "potion_stamina"
      ],
      [
        140,
        17,
        false,
        -72,
        985
      ],
      [
        143,
        31,
        false,
        -72,
        1095,
        -72,
        1095,
        "potion_mirage"
      ],
      [
        142,
        17,
        false,
        -72,
        1095
      ],
      [
        144,
        24,
        false,
        1,
        961,
        0,
        false
      ],
      [
        145,
        24,
        false,
        31,
        982,
        1,
        false
      ],
      [
        146,
        24,
        false,
        -6,
        997,
        2,
        false
      ],
      [
        147,
        41,
        false,
        38,
        1032,
        73,
        false,
        null
      ],
      [
        148,
        25,
        false,
        -1216,
        -671,
        0,
        true,
        false
      ],
      [
        149,
        25,
        false,
        -1216,
        -924,
        0,
        true,
        false
      ],
      [
        151,
        31,
        false,
        -1240,
        -885,
        -1240,
        -885,
        "mine"
      ],
      [
        150,
        17,
        false,
        -1240,
        -885
      ],
      [
        153,
        31,
        false,
        -1128,
        -753,
        -1128,
        -753,
        "potion_haste"
      ],
      [
        152,
        17,
        false,
        -1128,
        -753
      ],
      [
        154,
        24,
        false,
        -1191,
        -831,
        0,
        false
      ],
      [
        155,
        24,
        false,
        -1166,
        -808,
        1,
        false
      ],
      [
        156,
        24,
        false,
        -1155,
        -846,
        5,
        false
      ],
      [
        157,
        24,
        false,
        -1210,
        -775,
        7,
        false
      ],
      [
        159,
        31,
        false,
        -1864,
        875,
        -1864,
        875,
        "bomb"
      ],
      [
        158,
        17,
        false,
        -1864,
        875
      ],
      [
        161,
        31,
        false,
        1592,
        666,
        1592,
        666,
        "mine"
      ],
      [
        160,
        17,
        false,
        1592,
        666
      ],
      [
        162,
        39,
        false,
        1472,
        781,
        false,
        -1
      ],
      [
        163,
        24,
        false,
        1473,
        632,
        2,
        false
      ],
      [
        164,
        24,
        false,
        1522,
        630,
        1,
        false
      ],
      [
        165,
        24,
        false,
        1497,
        675,
        0,
        false
      ],
      [
        166,
        24,
        false,
        1453,
        696,
        14,
        false
      ],
      [
        167,
        24,
        false,
        1536,
        668,
        15,
        false
      ],
      [
        168,
        41,
        false,
        1556,
        637,
        73,
        false,
        null
      ],
      [
        170,
        31,
        false,
        1496,
        50,
        1496,
        50,
        "armor"
      ],
      [
        169,
        17,
        false,
        1496,
        50
      ],
      [
        172,
        31,
        false,
        1640,
        50,
        1640,
        50,
        "potion_mirage"
      ],
      [
        171,
        17,
        false,
        1640,
        50
      ],
      [
        173,
        24,
        false,
        1448,
        -10,
        0,
        false
      ],
      [
        174,
        24,
        false,
        1485,
        -10,
        1,
        false
      ],
      [
        175,
        24,
        false,
        1448,
        27,
        2,
        false
      ],
      [
        176,
        24,
        false,
        1567,
        -16,
        4,
        false
      ],
      [
        177,
        24,
        false,
        1594,
        -9,
        3,
        false
      ],
      [
        178,
        24,
        false,
        1678,
        -5,
        5,
        false
      ],
      [
        179,
        24,
        false,
        1687,
        92,
        6,
        false
      ],
      [
        180,
        24,
        false,
        1446,
        105,
        7,
        false
      ],
      [
        181,
        24,
        false,
        1485,
        109,
        8,
        false
      ],
      [
        182,
        39,
        false,
        1536,
        165,
        false,
        -1
      ],
      [
        183,
        41,
        false,
        1565,
        45,
        73,
        false,
        null
      ],
      [
        184,
        13,
        false,
        1327,
        718,
        78,
        false,
        0,
        [
          43
        ],
        20,
        3,
        1,
        "Kseltas",
        false,
        40,
        8,
        0,
        2,
        "ad",
        "female",
        0,
        1477,
        55,
        79,
        64,
        48,
        {},
        49,
        0
      ],
      [
        191,
        31,
        false,
        -120,
        -514,
        -106,
        -514,
        "bone_1"
      ],
      [
        200,
        31,
        false,
        1308,
        744,
        1261,
        607,
        "bone_4"
      ],
      [
        201,
        31,
        false,
        1213,
        530,
        1261,
        607,
        "bone_1"
      ],
      [
        210,
        31,
        false,
        -305,
        -476,
        -254,
        -507,
        "wood"
      ],
      [
        211,
        31,
        false,
        -154,
        -447,
        -254,
        -507,
        "yellow_orb"
      ],
      [
        212,
        31,
        false,
        -204,
        -558,
        -254,
        -507,
        "bone_2"
      ],
      [
        213,
        31,
        false,
        -204,
        -518,
        -254,
        -507,
        "bone_1"
      ],
      [
        214,
        31,
        false,
        -351,
        -420,
        -254,
        -507,
        "bone_1"
      ],
      [
        215,
        31,
        false,
        -172,
        -466,
        -254,
        -507,
        "bone_1"
      ],
      [
        216,
        31,
        false,
        -290,
        -561,
        -254,
        -507,
        "bronze_coin"
      ],
      [
        217,
        31,
        false,
        -367,
        -470,
        -254,
        -507,
        "bronze_coin"
      ],
      [
        225,
        31,
        false,
        -251,
        -320,
        -304,
        -359,
        "health_orb"
      ],
      [
        226,
        31,
        false,
        -281,
        -289,
        -304,
        -359,
        "bone_3"
      ],
      [
        227,
        31,
        false,
        -302,
        -489,
        -304,
        -359,
        "bone_1"
      ],
      [
        228,
        31,
        false,
        -255,
        -309,
        -304,
        -359,
        "bone_1"
      ],
      [
        229,
        31,
        false,
        -361,
        -326,
        -304,
        -359,
        "silver_coin"
      ],
      [
        235,
        31,
        false,
        1276,
        1059,
        1294,
        982,
        "bone_1"
      ],
      [
        238,
        31,
        false,
        1220,
        1093,
        1294,
        982,
        "bone_1"
      ],
      [
        239,
        31,
        false,
        1221,
        991,
        1294,
        982,
        "bone_4"
      ],
      [
        240,
        31,
        false,
        1186,
        990,
        1294,
        982,
        "bone_1"
      ],
      [
        241,
        31,
        false,
        1267,
        860,
        1294,
        982,
        "bronze_coin"
      ],
      [
        242,
        31,
        false,
        1214,
        1041,
        1294,
        982,
        "silver_coin"
      ],
      [
        243,
        31,
        false,
        1388,
        945,
        1294,
        982,
        "bronze_coin"
      ],
      [
        244,
        13,
        false,
        -1770,
        -1110,
        78,
        false,
        12,
        [
          43
        ],
        2,
        0,
        0,
        "Bifur",
        false,
        60,
        8,
        0,
        0,
        "",
        "human",
        0,
        1486,
        66,
        56,
        99,
        48,
        {},
        49,
        0
      ],
      [
        246,
        13,
        false,
        1250,
        1065,
        78,
        false,
        12,
        [
          83
        ],
        44,
        0,
        1,
        "Aeacat_III",
        false,
        80,
        8,
        0,
        1,
        "us",
        "female",
        0,
        1498,
        100,
        79,
        64,
        48,
        {},
        101,
        0
      ],
      [
        247,
        31,
        false,
        1403,
        742,
        1397,
        749,
        "wood"
      ],
      [
        248,
        31,
        false,
        1395,
        741,
        1397,
        749,
        "health_orb"
      ],
      [
        249,
        31,
        false,
        1406,
        743,
        1397,
        749,
        "yellow_orb"
      ],
      [
        250,
        31,
        false,
        1375,
        743,
        1397,
        749,
        "bone_2"
      ],
      [
        251,
        31,
        false,
        1382,
        739,
        1397,
        749,
        "bone_2"
      ],
      [
        252,
        31,
        false,
        1371,
        747,
        1397,
        749,
        "bone_4"
      ],
      [
        253,
        31,
        false,
        1396,
        741,
        1397,
        749,
        "bone_1"
      ],
      [
        254,
        31,
        false,
        1376,
        742,
        1397,
        749,
        "bone_1"
      ],
      [
        255,
        31,
        false,
        1406,
        749,
        1397,
        749,
        "gold_coin"
      ],
      [
        256,
        31,
        false,
        1411,
        749,
        1397,
        749,
        "bronze_coin"
      ],
      [
        257,
        13,
        false,
        -1680,
        -1161,
        78,
        false,
        0,
        [
          43
        ],
        0,
        0,
        0,
        "Thorin",
        false,
        80,
        8,
        0,
        0,
        "",
        "human",
        0,
        1513,
        66,
        56,
        99,
        48,
        {},
        49,
        0
      ]
    ],
    "mode": "fun",
    "ended": false,
    "lifetime": 37.41300000000037,
    "mapData": "{\"map\":{\"-25,-33\":{\"ground\":0},\"-24,-33\":{\"ground\":0},\"-23,-33\":{\"ground\":0},\"-25,-32\":{\"ground\":0},\"-22,-32\":{\"ground\":0},\"-21,-32\":{\"ground\":0},\"-27,-31\":{\"wall\":0},\"-25,-31\":{\"ground\":0},\"-24,-31\":{\"ground\":0},\"-23,-31\":{\"ground\":0},\"-22,-31\":{\"ground\":0},\"-21,-31\":{\"ground\":0},\"-30,-30\":{\"wall\":222},\"-29,-30\":{\"wall\":195},\"-28,-30\":{\"wall\":195},\"-27,-30\":{\"wall\":195},\"-26,-30\":{\"wall\":256},\"-23,-30\":{\"ground\":0},\"-22,-30\":{\"ground\":0},\"-21,-30\":{\"ground\":0},\"-30,-29\":{\"wall\":200},\"-29,-29\":{\"semi\":267},\"-28,-29\":{\"semi\":267},\"-27,-29\":{\"semi\":267},\"-26,-29\":{\"wall\":203},\"-22,-29\":{\"ground\":0},\"-21,-29\":{\"ground\":0},\"-30,-28\":{\"wall\":200},\"-29,-28\":{\"semi\":267},\"-28,-28\":{\"semi\":267},\"-27,-28\":{\"semi\":267},\"-26,-28\":{\"wall\":203},\"-25,-28\":{\"ground\":0},\"-23,-28\":{\"ground\":0},\"-22,-28\":{\"ground\":0},\"-21,-28\":{\"ground\":0},\"18,-28\":{\"wall\":244,\"ground\":255},\"19,-28\":{\"wall\":250,\"ground\":255},\"20,-28\":{\"wall\":250,\"ground\":255},\"21,-28\":{\"wall\":250,\"ground\":255},\"22,-28\":{\"wall\":245,\"ground\":255},\"-30,-27\":{\"wall\":200},\"-29,-27\":{\"semi\":267},\"-28,-27\":{\"semi\":267},\"-27,-27\":{\"semi\":267},\"-26,-27\":{\"wall\":203},\"-23,-27\":{\"ground\":0},\"-22,-27\":{\"ground\":0},\"-21,-27\":{\"ground\":0},\"-15,-27\":{\"wall\":244,\"ground\":266},\"-14,-27\":{\"wall\":250,\"ground\":266},\"-13,-27\":{\"wall\":245,\"ground\":266},\"18,-27\":{\"wall\":249,\"ground\":255},\"19,-27\":{\"ground\":255},\"20,-27\":{\"ground\":255},\"21,-27\":{\"ground\":255},\"22,-27\":{\"wall\":251,\"ground\":255},\"-30,-26\":{\"wall\":200},\"-29,-26\":{\"semi\":267},\"-28,-26\":{\"semi\":267},\"-27,-26\":{\"semi\":267},\"-26,-26\":{\"wall\":203},\"-25,-26\":{\"ground\":0},\"-23,-26\":{\"ground\":0},\"-22,-26\":{\"ground\":0},\"-21,-26\":{\"ground\":0},\"-15,-26\":{\"wall\":249,\"ground\":266},\"-14,-26\":{\"ground\":266},\"-13,-26\":{\"wall\":251,\"ground\":266},\"18,-26\":{\"wall\":249,\"ground\":255},\"19,-26\":{\"ground\":255},\"20,-26\":{\"ground\":255},\"21,-26\":{\"ground\":255},\"22,-26\":{\"wall\":251,\"ground\":255},\"-30,-25\":{\"wall\":218,\"semi\":267},\"-29,-25\":{\"wall\":219,\"semi\":267},\"-28,-25\":{\"wall\":248,\"ground\":0,\"semi\":267},\"-27,-25\":{\"wall\":219,\"semi\":267},\"-26,-25\":{\"wall\":214,\"semi\":267},\"-25,-25\":{\"ground\":0},\"-23,-25\":{\"ground\":0},\"-22,-25\":{\"ground\":0},\"-15,-25\":{\"wall\":246,\"ground\":266},\"-14,-25\":{\"wall\":248,\"ground\":266},\"-13,-25\":{\"wall\":247,\"ground\":266},\"5,-25\":{\"ground\":173},\"6,-25\":{\"ground\":151},\"7,-25\":{\"ground\":144},\"18,-25\":{\"wall\":246,\"ground\":255},\"19,-25\":{\"wall\":252,\"ground\":255},\"20,-25\":{\"wall\":248,\"ground\":255},\"21,-25\":{\"wall\":252,\"ground\":255},\"22,-25\":{\"wall\":247,\"ground\":255},\"-28,-24\":{\"semi\":268},\"3,-23\":{\"ground\":146},\"4,-23\":{\"ground\":151},\"20,-23\":{\"ground\":184},\"3,-22\":{\"ground\":176},\"20,-22\":{\"ground\":184},\"-20,-21\":{\"wall\":67,\"ground\":255},\"-19,-21\":{\"ground\":255},\"-18,-21\":{\"wall\":48,\"ground\":255},\"2,-21\":{\"ground\":173},\"20,-21\":{\"ground\":184},\"-20,-20\":{\"wall\":20,\"ground\":255},\"-19,-20\":{\"ground\":255},\"-18,-20\":{\"wall\":19,\"ground\":255},\"17,-20\":{\"ground\":181},\"18,-20\":{\"ground\":181},\"19,-20\":{\"ground\":181},\"21,-20\":{\"ground\":181},\"22,-20\":{\"ground\":181},\"23,-20\":{\"ground\":181},\"-20,-19\":{\"wall\":20,\"ground\":255},\"-19,-19\":{\"ground\":255},\"-18,-19\":{\"wall\":19,\"ground\":255},\"20,-19\":{\"ground\":184},\"-20,-18\":{\"wall\":20,\"ground\":255},\"-19,-18\":{\"ground\":255},\"-18,-18\":{\"wall\":19,\"ground\":255},\"20,-18\":{\"ground\":184},\"-20,-17\":{\"wall\":20,\"ground\":255},\"-19,-17\":{\"ground\":255},\"-18,-17\":{\"wall\":19,\"ground\":255},\"20,-17\":{\"ground\":184},\"-20,-16\":{\"wall\":49,\"ground\":255},\"-19,-16\":{\"ground\":255},\"-18,-16\":{\"wall\":70,\"ground\":255},\"-7,-16\":{\"wall\":244,\"ground\":266},\"-6,-16\":{\"wall\":245,\"ground\":266},\"-7,-15\":{\"wall\":249,\"ground\":266},\"-6,-15\":{\"wall\":251,\"ground\":266},\"7,-15\":{\"wall\":252},\"6,-14\":{\"wall\":251},\"7,-14\":{\"wall\":248,\"ground\":266},\"8,-14\":{\"wall\":249},\"-3,-13\":{\"wall\":244,\"ground\":266},\"-2,-13\":{\"wall\":245,\"ground\":266},\"-3,-12\":{\"wall\":249,\"ground\":266},\"-2,-12\":{\"wall\":251,\"ground\":266},\"-21,-9\":{\"wall\":244,\"ground\":241},\"-20,-9\":{\"wall\":250,\"ground\":241},\"-19,-9\":{\"wall\":250,\"ground\":241},\"-18,-9\":{\"wall\":245,\"ground\":241},\"-21,-8\":{\"wall\":249,\"ground\":241},\"-20,-8\":{\"ground\":241},\"-19,-8\":{\"ground\":241},\"-18,-8\":{\"wall\":251,\"ground\":241},\"-5,-8\":{\"ground\":0},\"13,-8\":{\"ground\":157},\"14,-8\":{\"ground\":174},\"15,-8\":{\"ground\":159},\"16,-8\":{\"ground\":160},\"17,-8\":{\"ground\":162},\"18,-8\":{\"ground\":163},\"19,-8\":{\"ground\":161},\"20,-8\":{\"ground\":166},\"21,-8\":{\"ground\":167},\"22,-8\":{\"ground\":168},\"23,-8\":{\"ground\":169},\"24,-8\":{\"ground\":170},\"25,-8\":{\"ground\":164},\"26,-8\":{\"ground\":165},\"-21,-7\":{\"wall\":249,\"ground\":241},\"-20,-7\":{\"ground\":241},\"-19,-7\":{\"ground\":241},\"-18,-7\":{\"wall\":251,\"ground\":241},\"-1,-7\":{\"wall\":244,\"ground\":241},\"0,-7\":{\"wall\":250,\"ground\":241},\"1,-7\":{\"wall\":245,\"ground\":241},\"-30,-6\":{\"ground\":146},\"-29,-6\":{\"ground\":152},\"-21,-6\":{\"wall\":246,\"ground\":241},\"-20,-6\":{\"wall\":252,\"ground\":241},\"-19,-6\":{\"wall\":248,\"ground\":241},\"-18,-6\":{\"wall\":247,\"ground\":241},\"-1,-6\":{\"wall\":249,\"ground\":241},\"0,-6\":{\"ground\":241},\"1,-6\":{\"wall\":251,\"ground\":241},\"-1,-5\":{\"wall\":246,\"ground\":241},\"0,-5\":{\"wall\":0,\"ground\":241},\"1,-5\":{\"wall\":247,\"ground\":241},\"-30,-4\":{\"ground\":147},\"-29,-4\":{\"ground\":154},\"-5,-4\":{\"wall\":222,\"ground\":0},\"-4,-4\":{\"wall\":195},\"-3,-4\":{\"wall\":195},\"-2,-4\":{\"wall\":195},\"-1,-4\":{\"wall\":0,\"semi\":267},\"0,-4\":{\"wall\":0,\"semi\":267},\"1,-4\":{\"wall\":0,\"semi\":267},\"2,-4\":{\"wall\":195},\"3,-4\":{\"wall\":195},\"4,-4\":{\"wall\":195},\"5,-4\":{\"wall\":256},\"-5,-3\":{\"wall\":200},\"-1,-3\":{\"semi\":268},\"0,-3\":{\"semi\":268},\"1,-3\":{\"semi\":268},\"5,-3\":{\"wall\":203},\"-30,-2\":{\"ground\":148},\"-29,-2\":{\"ground\":155},\"-18,-2\":{\"wall\":222},\"-17,-2\":{\"wall\":195},\"-16,-2\":{\"wall\":256},\"-5,-2\":{\"wall\":200},\"5,-2\":{\"wall\":203},\"-18,-1\":{\"wall\":200},\"-17,-1\":{\"semi\":267},\"-16,-1\":{\"wall\":203},\"-5,-1\":{\"wall\":200},\"5,-1\":{\"wall\":203},\"22,-1\":{\"wall\":67,\"ground\":240},\"23,-1\":{\"wall\":64,\"ground\":240},\"24,-1\":{\"wall\":69,\"ground\":240},\"25,-1\":{\"wall\":64,\"ground\":240},\"26,-1\":{\"wall\":48,\"ground\":240},\"-30,0\":{\"ground\":147},\"-29,0\":{\"ground\":154},\"-18,0\":{\"wall\":218},\"-17,0\":{\"wall\":206,\"semi\":268},\"-16,0\":{\"wall\":214},\"-5,0\":{\"wall\":200,\"ground\":0},\"-1,0\":{\"wall\":222},\"0,0\":{\"wall\":195},\"1,0\":{\"wall\":256},\"5,0\":{\"wall\":203},\"22,0\":{\"wall\":20,\"ground\":240},\"23,0\":{\"ground\":240},\"24,0\":{\"ground\":240},\"25,0\":{\"ground\":240},\"26,0\":{\"wall\":19,\"ground\":240},\"-5,1\":{\"wall\":200,\"ground\":0},\"-1,1\":{\"wall\":200},\"0,1\":{\"semi\":267},\"1,1\":{\"wall\":203},\"5,1\":{\"wall\":203},\"22,1\":{\"wall\":20,\"ground\":240},\"23,1\":{\"ground\":240},\"24,1\":{\"ground\":240},\"25,1\":{\"ground\":240},\"26,1\":{\"wall\":19,\"ground\":240},\"-30,2\":{\"ground\":148},\"-29,2\":{\"ground\":154},\"-5,2\":{\"wall\":200,\"ground\":0},\"-1,2\":{\"semi\":268},\"0,2\":{\"semi\":268},\"1,2\":{\"semi\":268},\"5,2\":{\"wall\":203},\"22,2\":{\"wall\":20,\"ground\":240},\"23,2\":{\"ground\":240},\"24,2\":{\"ground\":240},\"25,2\":{\"ground\":240},\"26,2\":{\"wall\":19,\"ground\":240},\"-5,3\":{\"wall\":200,\"ground\":0},\"5,3\":{\"wall\":203},\"22,3\":{\"wall\":49,\"ground\":240},\"23,3\":{\"wall\":68,\"ground\":240},\"24,3\":{\"wall\":51,\"ground\":240},\"25,3\":{\"wall\":68,\"ground\":240},\"26,3\":{\"wall\":70,\"ground\":240},\"-30,4\":{\"ground\":147},\"-29,4\":{\"ground\":154},\"-5,4\":{\"wall\":200,\"ground\":0},\"5,4\":{\"wall\":203},\"-5,5\":{\"wall\":200,\"ground\":0},\"5,5\":{\"wall\":203},\"-30,6\":{\"ground\":148},\"-29,6\":{\"ground\":154},\"-5,6\":{\"wall\":218,\"ground\":0},\"-4,6\":{\"wall\":219},\"-3,6\":{\"wall\":219},\"-2,6\":{\"wall\":219},\"2,6\":{\"wall\":219},\"3,6\":{\"wall\":219},\"4,6\":{\"wall\":219},\"5,6\":{\"wall\":214},\"-30,8\":{\"ground\":147},\"-29,8\":{\"ground\":154},\"17,8\":{\"ground\":157},\"18,8\":{\"ground\":174},\"19,8\":{\"ground\":159},\"20,8\":{\"ground\":160},\"21,8\":{\"ground\":166},\"22,8\":{\"ground\":167},\"23,8\":{\"ground\":164},\"24,8\":{\"ground\":165},\"-15,9\":{\"ground\":146},\"-14,9\":{\"ground\":152},\"-30,10\":{\"ground\":148},\"-29,10\":{\"ground\":155},\"-12,11\":{\"ground\":142},\"-11,11\":{\"ground\":145},\"-15,12\":{\"ground\":149},\"-14,12\":{\"ground\":153},\"-30,13\":{\"ground\":149},\"-29,13\":{\"ground\":153},\"-12,13\":{\"ground\":143},\"14,13\":{\"wall\":251},\"15,13\":{\"wall\":248,\"ground\":266},\"16,13\":{\"wall\":249},\"22,13\":{\"wall\":244,\"ground\":240},\"23,13\":{\"wall\":250,\"ground\":240},\"24,13\":{\"wall\":250,\"ground\":240},\"25,13\":{\"wall\":245,\"ground\":240},\"-11,14\":{\"ground\":144},\"22,14\":{\"wall\":249,\"ground\":240},\"23,14\":{\"ground\":240},\"24,14\":{\"ground\":240},\"25,14\":{\"wall\":251,\"ground\":240},\"22,15\":{\"wall\":249,\"ground\":240},\"23,15\":{\"ground\":240},\"24,15\":{\"ground\":240},\"25,15\":{\"wall\":251,\"ground\":240},\"17,16\":{\"wall\":251},\"18,16\":{\"wall\":248,\"ground\":266},\"19,16\":{\"wall\":249},\"22,16\":{\"wall\":249,\"ground\":240},\"23,16\":{\"ground\":240},\"24,16\":{\"ground\":240},\"25,16\":{\"wall\":251,\"ground\":240},\"22,17\":{\"wall\":246,\"ground\":240},\"23,17\":{\"wall\":248,\"ground\":240},\"24,17\":{\"wall\":252,\"ground\":240},\"25,17\":{\"wall\":247,\"ground\":240},\"-31,18\":{\"ground\":146},\"-30,18\":{\"ground\":151},\"-29,18\":{\"ground\":150},\"-28,18\":{\"ground\":152},\"-16,18\":{\"wall\":67,\"ground\":240},\"-15,18\":{\"wall\":69,\"ground\":240},\"-14,18\":{\"wall\":48,\"ground\":240},\"-16,19\":{\"wall\":20,\"ground\":240},\"-15,19\":{\"ground\":240},\"-14,19\":{\"wall\":19,\"ground\":240},\"-31,20\":{\"ground\":147},\"-28,20\":{\"ground\":154},\"-16,20\":{\"wall\":49,\"ground\":240},\"-15,20\":{\"wall\":51,\"ground\":240},\"-14,20\":{\"wall\":70,\"ground\":240},\"-2,21\":{\"wall\":67,\"ground\":240},\"-1,21\":{\"wall\":69,\"ground\":240},\"0,21\":{\"wall\":69,\"ground\":240},\"1,21\":{\"wall\":69,\"ground\":240},\"2,21\":{\"wall\":48,\"ground\":240},\"-2,22\":{\"wall\":20,\"ground\":240},\"-1,22\":{\"ground\":240},\"0,22\":{\"ground\":240},\"1,22\":{\"ground\":240},\"2,22\":{\"wall\":19,\"ground\":240},\"25,22\":{\"ground\":0},\"26,22\":{\"ground\":0},\"27,22\":{\"ground\":0},\"-31,23\":{\"ground\":149},\"-30,23\":{\"ground\":166},\"-29,23\":{\"ground\":167},\"-28,23\":{\"ground\":153},\"-2,23\":{\"wall\":20,\"ground\":240},\"-1,23\":{\"ground\":240},\"0,23\":{\"ground\":240},\"1,23\":{\"ground\":240},\"2,23\":{\"wall\":19,\"ground\":240},\"25,23\":{\"ground\":0},\"28,23\":{\"ground\":0},\"29,23\":{\"ground\":0},\"-2,24\":{\"wall\":20,\"ground\":240},\"-1,24\":{\"ground\":240},\"0,24\":{\"ground\":240},\"1,24\":{\"ground\":240},\"2,24\":{\"wall\":19,\"ground\":240},\"23,24\":{\"wall\":0},\"25,24\":{\"ground\":0},\"26,24\":{\"ground\":0},\"27,24\":{\"ground\":0},\"28,24\":{\"ground\":0},\"29,24\":{\"ground\":0},\"-2,25\":{\"wall\":20,\"ground\":240},\"-1,25\":{\"ground\":240},\"0,25\":{\"ground\":240},\"1,25\":{\"ground\":240},\"2,25\":{\"wall\":19,\"ground\":240},\"20,25\":{\"wall\":222},\"21,25\":{\"wall\":195},\"22,25\":{\"wall\":195},\"23,25\":{\"wall\":195},\"24,25\":{\"wall\":256},\"27,25\":{\"ground\":0},\"28,25\":{\"ground\":0},\"29,25\":{\"ground\":0},\"-13,26\":{\"wall\":222},\"-12,26\":{\"wall\":195},\"-11,26\":{\"wall\":256},\"-2,26\":{\"wall\":49,\"ground\":240},\"-1,26\":{\"wall\":68,\"ground\":240},\"0,26\":{\"wall\":51,\"ground\":240},\"1,26\":{\"wall\":68,\"ground\":240},\"2,26\":{\"wall\":70,\"ground\":240},\"20,26\":{\"wall\":200},\"21,26\":{\"semi\":267},\"22,26\":{\"semi\":267},\"23,26\":{\"semi\":267},\"24,26\":{\"wall\":203},\"28,26\":{\"ground\":0},\"29,26\":{\"ground\":0},\"-19,27\":{\"wall\":244,\"ground\":242},\"-18,27\":{\"wall\":250,\"ground\":242},\"-17,27\":{\"wall\":250,\"ground\":242},\"-16,27\":{\"wall\":250,\"ground\":242},\"-15,27\":{\"wall\":245,\"ground\":242},\"-13,27\":{\"wall\":200},\"-12,27\":{\"semi\":267},\"-11,27\":{\"wall\":203},\"20,27\":{\"wall\":200},\"21,27\":{\"semi\":267},\"22,27\":{\"semi\":267},\"23,27\":{\"semi\":267},\"24,27\":{\"wall\":203},\"25,27\":{\"ground\":0},\"27,27\":{\"ground\":0},\"28,27\":{\"ground\":0},\"29,27\":{\"ground\":0},\"-19,28\":{\"wall\":249,\"ground\":242},\"-18,28\":{\"ground\":242},\"-17,28\":{\"ground\":242},\"-16,28\":{\"ground\":242},\"-15,28\":{\"wall\":251,\"ground\":242},\"-13,28\":{\"wall\":218},\"-12,28\":{\"wall\":206,\"semi\":268},\"-11,28\":{\"wall\":214},\"20,28\":{\"wall\":200},\"21,28\":{\"semi\":267},\"22,28\":{\"semi\":267},\"23,28\":{\"semi\":267},\"24,28\":{\"wall\":203},\"27,28\":{\"ground\":0},\"28,28\":{\"ground\":0},\"29,28\":{\"ground\":0},\"-19,29\":{\"wall\":249,\"ground\":242},\"-18,29\":{\"ground\":242},\"-17,29\":{\"ground\":242},\"-16,29\":{\"ground\":242},\"-15,29\":{\"wall\":251,\"ground\":242},\"20,29\":{\"wall\":200},\"21,29\":{\"semi\":267},\"22,29\":{\"semi\":267},\"23,29\":{\"semi\":267},\"24,29\":{\"wall\":203},\"25,29\":{\"ground\":0},\"27,29\":{\"ground\":0},\"28,29\":{\"ground\":0},\"29,29\":{\"ground\":0},\"-19,30\":{\"wall\":249,\"ground\":242},\"-18,30\":{\"ground\":242},\"-17,30\":{\"ground\":242},\"-16,30\":{\"ground\":242},\"-15,30\":{\"wall\":251,\"ground\":242},\"20,30\":{\"wall\":218,\"semi\":267},\"21,30\":{\"wall\":219,\"semi\":267},\"22,30\":{\"wall\":248,\"ground\":0,\"semi\":267},\"23,30\":{\"wall\":219,\"semi\":267},\"24,30\":{\"wall\":214,\"semi\":267},\"25,30\":{\"ground\":0},\"27,30\":{\"ground\":0},\"28,30\":{\"ground\":0},\"-19,31\":{\"wall\":246,\"ground\":242},\"-18,31\":{\"wall\":252,\"ground\":242},\"-17,31\":{\"wall\":248,\"ground\":242},\"-16,31\":{\"wall\":252,\"ground\":242},\"-15,31\":{\"wall\":247,\"ground\":242},\"22,31\":{\"semi\":268}},\"entities\":[{\"key\":\"door_unlocked\",\"x\":-1792,\"y\":-1067,\"local\":{\"team\":0},\"sandbox_id\":31},{\"key\":\"respawnA\",\"x\":-1837,\"y\":-1276,\"sandbox_id\":31},{\"key\":\"respawnA\",\"x\":-1675,\"y\":-1278,\"sandbox_id\":31},{\"key\":\"respawnA\",\"x\":-1852,\"y\":-1160,\"sandbox_id\":31},{\"key\":\"respawnA\",\"x\":-1680,\"y\":-1161,\"sandbox_id\":31},{\"key\":\"respawnA\",\"x\":-1763,\"y\":-1238,\"sandbox_id\":31},{\"key\":\"stove\",\"x\":-1760,\"y\":-1298,\"sandbox_id\":31},{\"key\":\"orc_archer\",\"x\":-1773,\"y\":-1194,\"local\":{\"team\":0},\"sandbox_id\":31},{\"key\":\"door_unlocked\",\"x\":1408,\"y\":1353,\"local\":{\"team\":1},\"sandbox_id\":32},{\"key\":\"respawnB\",\"x\":1347,\"y\":1140,\"sandbox_id\":32},{\"key\":\"respawnB\",\"x\":1447,\"y\":1193,\"sandbox_id\":32},{\"key\":\"respawnB\",\"x\":1539,\"y\":1139,\"sandbox_id\":32},{\"key\":\"respawnB\",\"x\":1350,\"y\":1255,\"sandbox_id\":32},{\"key\":\"respawnB\",\"x\":1530,\"y\":1257,\"sandbox_id\":32},{\"key\":\"stove\",\"x\":1440,\"y\":1122,\"sandbox_id\":32},{\"key\":\"orc_archer\",\"x\":1437,\"y\":1232,\"local\":{\"team\":1},\"sandbox_id\":32},{\"key\":\"claimableFlag\",\"x\":31,\"y\":29,\"local\":{\"id\":\"flag\"},\"sandbox_id\":36},{\"key\":\"medical_cupboard1\",\"x\":92,\"y\":-287,\"sandbox_id\":36},{\"key\":\"palisadeGate\",\"x\":-64,\"y\":308,\"local\":{\"fort\":true},\"sandbox_id\":36},{\"key\":\"orc_archer\",\"x\":-286,\"y\":-165,\"local\":{\"fort\":true},\"sandbox_id\":36},{\"key\":\"orc_archer\",\"x\":-285,\"y\":247,\"local\":{\"fort\":true},\"sandbox_id\":36},{\"key\":\"orc_archer\",\"x\":338,\"y\":245,\"local\":{\"fort\":true},\"sandbox_id\":36},{\"key\":\"orc_archer\",\"x\":337,\"y\":-166,\"local\":{\"fort\":true},\"sandbox_id\":36},{\"key\":\"pedestal\",\"x\":248,\"y\":-71,\"sandbox_id\":36},{\"key\":\"flag_doodle\",\"x\":-59,\"y\":196,\"local\":{\"fort\":true},\"sandbox_id\":36},{\"key\":\"flag_doodle\",\"x\":124,\"y\":194,\"local\":{\"fort\":true},\"sandbox_id\":36},{\"key\":\"flag_doodle\",\"x\":377,\"y\":-275,\"local\":{\"fort\":true},\"sandbox_id\":36},{\"key\":\"flag_doodle\",\"x\":-317,\"y\":-270,\"local\":{\"fort\":true},\"sandbox_id\":36},{\"key\":\"markerFort\",\"x\":52,\"y\":18,\"local\":{\"text\":\"fort\"},\"sandbox_id\":36},{\"key\":\"armory_wardrobe1\",\"x\":-16,\"y\":-275,\"sandbox_id\":36},{\"key\":\"stove\",\"x\":32,\"y\":-286,\"sandbox_id\":36},{\"key\":\"random0\",\"x\":1192,\"y\":-968,\"sandbox_id\":38},{\"key\":\"random1\",\"x\":1447,\"y\":-975,\"sandbox_id\":38},{\"key\":\"random1\",\"x\":1201,\"y\":-749,\"sandbox_id\":38},{\"key\":\"random0\",\"x\":1430,\"y\":-729,\"sandbox_id\":38},{\"key\":\"claimableFlag\",\"x\":1309,\"y\":-855,\"sandbox_id\":38},{\"key\":\"door_unlocked\",\"x\":1280,\"y\":-1067,\"local\":{\"team\":2,\"fort\":true},\"sandbox_id\":38},{\"key\":\"barbarian_miner\",\"x\":1099,\"y\":-922,\"local\":{\"fort\":true},\"sandbox_id\":38},{\"key\":\"barbarian_sentry\",\"x\":1509,\"y\":-765,\"local\":{\"fort\":true},\"sandbox_id\":38},{\"key\":\"barbarian_sentry\",\"x\":1085,\"y\":-745,\"local\":{\"fort\":true},\"sandbox_id\":38},{\"key\":\"crate18\",\"x\":1315,\"y\":-1174,\"sandbox_id\":38},{\"key\":\"crate15\",\"x\":1240,\"y\":-992,\"sandbox_id\":38},{\"key\":\"crate15\",\"x\":1240,\"y\":-961,\"sandbox_id\":38},{\"key\":\"crate15\",\"x\":1156,\"y\":-692,\"sandbox_id\":38},{\"key\":\"crate14\",\"x\":1191,\"y\":-692,\"sandbox_id\":38},{\"key\":\"crate14\",\"x\":1244,\"y\":-930,\"sandbox_id\":38},{\"key\":\"crate14\",\"x\":1408,\"y\":-920,\"sandbox_id\":38},{\"key\":\"crate14\",\"x\":1480,\"y\":-679,\"sandbox_id\":38},{\"key\":\"crate13\",\"x\":1480,\"y\":-706,\"sandbox_id\":38},{\"key\":\"crate13\",\"x\":1480,\"y\":-730,\"sandbox_id\":38},{\"key\":\"crate12\",\"x\":1448,\"y\":-924,\"sandbox_id\":38},{\"key\":\"crate11\",\"x\":1230,\"y\":-693,\"sandbox_id\":38},{\"key\":\"crate11\",\"x\":1473,\"y\":-921,\"sandbox_id\":38},{\"key\":\"crate0\",\"x\":1136,\"y\":-983,\"sandbox_id\":38},{\"key\":\"crate1\",\"x\":1136,\"y\":-943,\"sandbox_id\":38},{\"key\":\"crate3\",\"x\":1493,\"y\":-956,\"sandbox_id\":38},{\"key\":\"crate5\",\"x\":1106,\"y\":-699,\"sandbox_id\":38},{\"key\":\"pedestal\",\"x\":1192,\"y\":-1193,\"sandbox_id\":38},{\"key\":\"pedestal\",\"x\":1432,\"y\":-1193,\"sandbox_id\":38},{\"key\":\"crate1\",\"x\":1218,\"y\":-1127,\"sandbox_id\":38},{\"key\":\"crate2\",\"x\":1245,\"y\":-1151,\"sandbox_id\":38},{\"key\":\"crate0\",\"x\":1217,\"y\":-1163,\"sandbox_id\":38},{\"key\":\"crate5\",\"x\":1405,\"y\":-1134,\"sandbox_id\":38},{\"key\":\"crate6\",\"x\":1381,\"y\":-1165,\"sandbox_id\":38},{\"key\":\"crate7\",\"x\":1367,\"y\":-1132,\"sandbox_id\":38},{\"key\":\"respawnD\",\"x\":-7,\"y\":446,\"sandbox_id\":33},{\"key\":\"respawnD\",\"x\":-455,\"y\":-1226,\"sandbox_id\":33},{\"key\":\"door_locked\",\"x\":-1088,\"y\":33,\"sandbox_id\":30},{\"key\":\"orc_archer\",\"x\":-1092,\"y\":-76,\"local\":{\"fort\":true},\"sandbox_id\":30},{\"key\":\"claimableFlag\",\"x\":-1050,\"y\":-49,\"sandbox_id\":30},{\"key\":\"respawnD\",\"x\":-1543,\"y\":226,\"sandbox_id\":33},{\"key\":\"tree\",\"x\":59,\"y\":-1333,\"sandbox_id\":35},{\"key\":\"tree\",\"x\":261,\"y\":-1200,\"sandbox_id\":35},{\"key\":\"tree\",\"x\":343,\"y\":-1436,\"sandbox_id\":35},{\"key\":\"orc_berserker\",\"x\":209,\"y\":-1288,\"sandbox_id\":35},{\"key\":\"orc_tank\",\"x\":137,\"y\":-1459,\"sandbox_id\":35},{\"key\":\"orc_warrior\",\"x\":308,\"y\":-1409,\"sandbox_id\":35},{\"key\":\"campfire\",\"x\":208,\"y\":-1375,\"sandbox_id\":35},{\"key\":\"stone0\",\"x\":475,\"y\":-499,\"sandbox_id\":37},{\"key\":\"stone1\",\"x\":502,\"y\":-476,\"sandbox_id\":37},{\"key\":\"stone15\",\"x\":465,\"y\":-474,\"sandbox_id\":37},{\"key\":\"stone4\",\"x\":507,\"y\":-508,\"sandbox_id\":37},{\"key\":\"stone5\",\"x\":491,\"y\":-457,\"sandbox_id\":37},{\"key\":\"stone6\",\"x\":526,\"y\":-488,\"sandbox_id\":37},{\"key\":\"stone7\",\"x\":521,\"y\":-461,\"sandbox_id\":37},{\"key\":\"crate5\",\"x\":479,\"y\":-596,\"sandbox_id\":37},{\"key\":\"barbarian_miner\",\"x\":403,\"y\":-517,\"sandbox_id\":37},{\"key\":\"barbarian_saper\",\"x\":986,\"y\":596,\"sandbox_id\":3},{\"key\":\"barbarian_miner\",\"x\":1177,\"y\":728,\"sandbox_id\":3},{\"key\":\"barbarian_sentry\",\"x\":1014,\"y\":712,\"sandbox_id\":3},{\"key\":\"crate5\",\"x\":1050,\"y\":721,\"sandbox_id\":3},{\"key\":\"crate7\",\"x\":1010,\"y\":733,\"sandbox_id\":3},{\"key\":\"crate6\",\"x\":1034,\"y\":752,\"sandbox_id\":3},{\"key\":\"stone15\",\"x\":985,\"y\":753,\"sandbox_id\":3},{\"key\":\"stone14\",\"x\":985,\"y\":724,\"sandbox_id\":3},{\"key\":\"stone13\",\"x\":959,\"y\":734,\"sandbox_id\":3},{\"key\":\"barbarian_giant\",\"x\":-866,\"y\":-972,\"sandbox_id\":2},{\"key\":\"crate18\",\"x\":-861,\"y\":-1140,\"sandbox_id\":2},{\"key\":\"door_locked\",\"x\":-896,\"y\":-1067,\"sandbox_id\":2},{\"key\":\"crate2\",\"x\":-416,\"y\":-675,\"sandbox_id\":1},{\"key\":\"crate1\",\"x\":-383,\"y\":-676,\"sandbox_id\":1},{\"key\":\"crate0\",\"x\":-353,\"y\":-647,\"sandbox_id\":1},{\"key\":\"crate3\",\"x\":-413,\"y\":-638,\"sandbox_id\":1},{\"key\":\"crate4\",\"x\":-350,\"y\":-677,\"sandbox_id\":1},{\"key\":\"crate8\",\"x\":-157,\"y\":-543,\"sandbox_id\":1},{\"key\":\"crate6\",\"x\":-106,\"y\":-539,\"sandbox_id\":1},{\"key\":\"crate7\",\"x\":-147,\"y\":-515,\"sandbox_id\":1},{\"key\":\"crate0\",\"x\":-106,\"y\":-514,\"sandbox_id\":1},{\"key\":\"barbarian_sentry\",\"x\":-389,\"y\":-532,\"sandbox_id\":1},{\"key\":\"barbarian_sentry\",\"x\":-262,\"y\":-433,\"sandbox_id\":1},{\"key\":\"campfire\",\"x\":-288,\"y\":-528,\"sandbox_id\":1},{\"key\":\"tree\",\"x\":-1827,\"y\":-790,\"sandbox_id\":34},{\"key\":\"tree\",\"x\":-1638,\"y\":-716,\"sandbox_id\":34},{\"key\":\"tree\",\"x\":-1820,\"y\":-614,\"sandbox_id\":34},{\"key\":\"orc_warrior\",\"x\":-1952,\"y\":-705,\"sandbox_id\":34},{\"key\":\"orc_warrior\",\"x\":-1693,\"y\":-845,\"sandbox_id\":34},{\"key\":\"orc_warrior\",\"x\":-1685,\"y\":-611,\"sandbox_id\":34},{\"key\":\"orc_tank\",\"x\":-1768,\"y\":-722,\"sandbox_id\":34},{\"key\":\"door_locked\",\"x\":-768,\"y\":1265,\"sandbox_id\":30},{\"key\":\"orc_archer\",\"x\":-772,\"y\":1156,\"local\":{\"fort\":true},\"sandbox_id\":30},{\"key\":\"claimableFlag\",\"x\":-730,\"y\":1183,\"sandbox_id\":30},{\"key\":\"respawnD\",\"x\":825,\"y\":-126,\"sandbox_id\":33},{\"key\":\"crate6\",\"x\":-971,\"y\":832,\"sandbox_id\":8},{\"key\":\"crate7\",\"x\":-971,\"y\":866,\"sandbox_id\":8},{\"key\":\"crate8\",\"x\":-922,\"y\":827,\"sandbox_id\":8},{\"key\":\"crate6\",\"x\":-879,\"y\":830,\"sandbox_id\":8},{\"key\":\"crate4\",\"x\":-869,\"y\":863,\"sandbox_id\":8},{\"key\":\"crate7\",\"x\":-899,\"y\":863,\"sandbox_id\":8},{\"key\":\"crate1\",\"x\":-929,\"y\":862,\"sandbox_id\":8},{\"key\":\"door_unlocked\",\"x\":-960,\"y\":913,\"sandbox_id\":8},{\"key\":\"markerHouse\",\"x\":-928,\"y\":840,\"sandbox_id\":8},{\"key\":\"orc_warrior\",\"x\":-1132,\"y\":1262,\"local\":{\"guardHouse\":true},\"sandbox_id\":10},{\"key\":\"pedestal\",\"x\":-968,\"y\":1326,\"sandbox_id\":10},{\"key\":\"crate5\",\"x\":-982,\"y\":1242,\"sandbox_id\":10},{\"key\":\"crate6\",\"x\":-939,\"y\":1253,\"sandbox_id\":10},{\"key\":\"crate7\",\"x\":-950,\"y\":1214,\"sandbox_id\":10},{\"key\":\"door_unlocked\",\"x\":-1088,\"y\":1397,\"sandbox_id\":10},{\"key\":\"markerHouse\",\"x\":-1054,\"y\":1260,\"sandbox_id\":10},{\"key\":\"door_unlocked\",\"x\":-1216,\"y\":-231,\"sandbox_id\":6},{\"key\":\"pedestal\",\"x\":-1288,\"y\":-335,\"sandbox_id\":6},{\"key\":\"crate5\",\"x\":-1199,\"y\":-349,\"sandbox_id\":6},{\"key\":\"crate6\",\"x\":-1149,\"y\":-312,\"sandbox_id\":6},{\"key\":\"crate7\",\"x\":-1150,\"y\":-354,\"sandbox_id\":6},{\"key\":\"crate13\",\"x\":-1123,\"y\":-339,\"sandbox_id\":6},{\"key\":\"crate16\",\"x\":-1116,\"y\":-376,\"sandbox_id\":6},{\"key\":\"markerHouse\",\"x\":-1218,\"y\":-326,\"sandbox_id\":6},{\"key\":\"respawnD\",\"x\":-840,\"y\":665,\"sandbox_id\":15},{\"key\":\"respawnD\",\"x\":-750,\"y\":403,\"sandbox_id\":15},{\"key\":\"door_unlocked\",\"x\":0,\"y\":1177,\"sandbox_id\":9},{\"key\":\"orc_warrior\",\"x\":101,\"y\":1039,\"local\":{\"guardHouse\":true},\"sandbox_id\":9},{\"key\":\"pedestal\",\"x\":-72,\"y\":985,\"sandbox_id\":9},{\"key\":\"pedestal\",\"x\":-72,\"y\":1095,\"sandbox_id\":9},{\"key\":\"crate0\",\"x\":1,\"y\":961,\"sandbox_id\":9},{\"key\":\"crate1\",\"x\":31,\"y\":982,\"sandbox_id\":9},{\"key\":\"crate2\",\"x\":-6,\"y\":997,\"sandbox_id\":9},{\"key\":\"markerHouse\",\"x\":38,\"y\":1032,\"sandbox_id\":9},{\"key\":\"guillotine\",\"x\":-1216,\"y\":-671,\"sandbox_id\":4},{\"key\":\"guillotine\",\"x\":-1216,\"y\":-924,\"sandbox_id\":4},{\"key\":\"pedestal\",\"x\":-1240,\"y\":-885,\"sandbox_id\":4},{\"key\":\"pedestal\",\"x\":-1128,\"y\":-753,\"sandbox_id\":4},{\"key\":\"crate0\",\"x\":-1191,\"y\":-831,\"sandbox_id\":4},{\"key\":\"crate1\",\"x\":-1166,\"y\":-808,\"sandbox_id\":4},{\"key\":\"crate5\",\"x\":-1155,\"y\":-846,\"sandbox_id\":4},{\"key\":\"crate7\",\"x\":-1210,\"y\":-775,\"sandbox_id\":4},{\"key\":\"pedestal\",\"x\":-1864,\"y\":875,\"sandbox_id\":24},{\"key\":\"pedestal\",\"x\":1592,\"y\":666,\"sandbox_id\":5},{\"key\":\"door_unlocked\",\"x\":1472,\"y\":781,\"sandbox_id\":5},{\"key\":\"crate2\",\"x\":1473,\"y\":632,\"sandbox_id\":5},{\"key\":\"crate1\",\"x\":1522,\"y\":630,\"sandbox_id\":5},{\"key\":\"crate0\",\"x\":1497,\"y\":675,\"sandbox_id\":5},{\"key\":\"crate14\",\"x\":1453,\"y\":696,\"sandbox_id\":5},{\"key\":\"crate15\",\"x\":1536,\"y\":668,\"sandbox_id\":5},{\"key\":\"markerHouse\",\"x\":1556,\"y\":637,\"sandbox_id\":5},{\"key\":\"pedestal\",\"x\":1496,\"y\":50,\"sandbox_id\":7},{\"key\":\"pedestal\",\"x\":1640,\"y\":50,\"sandbox_id\":7},{\"key\":\"crate0\",\"x\":1448,\"y\":-10,\"sandbox_id\":7},{\"key\":\"crate1\",\"x\":1485,\"y\":-10,\"sandbox_id\":7},{\"key\":\"crate2\",\"x\":1448,\"y\":27,\"sandbox_id\":7},{\"key\":\"crate4\",\"x\":1567,\"y\":-16,\"sandbox_id\":7},{\"key\":\"crate3\",\"x\":1594,\"y\":-9,\"sandbox_id\":7},{\"key\":\"crate5\",\"x\":1678,\"y\":-5,\"sandbox_id\":7},{\"key\":\"crate6\",\"x\":1687,\"y\":92,\"sandbox_id\":7},{\"key\":\"crate7\",\"x\":1446,\"y\":105,\"sandbox_id\":7},{\"key\":\"crate8\",\"x\":1485,\"y\":109,\"sandbox_id\":7},{\"key\":\"door_unlocked\",\"x\":1536,\"y\":165,\"sandbox_id\":7},{\"key\":\"markerHouse\",\"x\":1565,\"y\":45,\"sandbox_id\":7}]}"
  }
]